jenkins_jobs_slack
