Metadata-Version: 1.1
Name: jenkins-jobs-slack
Version: 0.3.2
Summary: Jenkins Job Builder Slack Notifier
Home-page: https://github.com/asmundg/jenkins-jobs-slack
Author: Aasmund Grammeltvedt
Author-email: asmundg@big-oil.org
License: MIT license
Platform: UNKNOWN
Classifier: Environment :: Console
Classifier: Intended Audience :: Developers
Classifier: Intended Audience :: Information Technology
Classifier: License :: OSI Approved :: Apache Software License
Classifier: Operating System :: OS Independent
Classifier: Programming Language :: Python
Classifier: Programming Language :: Python :: 2
Classifier: Programming Language :: Python :: 3
